{
	"name": "DropFileTest",
	"properties": {
		"activities": [
			{
				"name": "setSourceSystemName",
				"type": "SetVariable",
				"dependsOn": [],
				"userProperties": [],
				"typeProperties": {
					"variableName": "varSourceSystemName",
					"value": {
						"value": "@json(pipeline().parameters.PipelineParamaters)",
						"type": "Expression"
					}
				}
			}
		],
		"parameters": {
			"PipelineParamaters": {
				"type": "string",
				"defaultValue": {
					"IngestID": 12,
					"SourceSystemName": "ManualCRM",
					"StreamName": "Customers",
					"Backend": "CSV",
					"DataFormat": null,
					"SourceFileDropFileSystem": "drop-zone",
					"SourceFileDropFolder": "Manual",
					"SourceFileDropFile": "ManualCRM_Customers_20221021.csv",
					"SourceFileDelimiter": ",",
					"SourceFileHeaderFlag": true,
					"DestinationRawFileSystem": "raw-zone",
					"DestinationRawFolder": "manual/customers/2022-10",
					"DestinationRawFile": "customers_20221021_GUID.json",
					"DataMapping": null,
					"ReloadFlag": false,
					"L1TransformationReqdFlag": true,
					"L2TransformationReqdFlag": true,
					"DelayL1TransformationFlag": false,
					"DelayL2TransformationFlag": true,
					"ADFPipelineRunID": null
				}
			}
		},
		"variables": {
			"varSourceSystemName": {
				"type": "String"
			}
		},
		"annotations": []
	}
}