{
	"name": "RestAnonymous",
	"properties": {
		"linkedServiceName": {
			"referenceName": "Rest Anonymous",
			"type": "LinkedServiceReference",
			"parameters": {
				"KeyVaultSecret-APIKey": {
					"value": "@dataset().KeyVaultSecretAPIKey",
					"type": "Expression"
				}
			}
		},
		"parameters": {
			"KeyVaultSecretAPIKey": {
				"type": "string"
			},
			"APIURL": {
				"type": "string"
			}
		},
		"annotations": [],
		"type": "RestResource",
		"typeProperties": {
			"relativeUrl": {
				"value": "@concat(dataset().APIURL, dataset().KeyVaultSecretAPIKey)",
				"type": "Expression"
			}
		},
		"schema": []
	}
}